{
  "_fv": 13,
  "_type": "biome",
  "definition": {
    "name": "Black Desert",
    "groundBlock": {
      "value": "CUSTOM:DarkSand"
    },
    "undergroundBlock": {
      "value": "Blocks.STONE#0"
    },
    "treeType": 0,
    "vanillaTreeType": "Default",
    "minHeight": 7,
    "spawnVines": false,
    "treeVines": {
      "value": ""
    },
    "treeStem": {
      "value": ""
    },
    "treeBranch": {
      "value": ""
    },
    "treeFruits": {
      "value": ""
    },
    "airColor": {
      "value": -15987700,
      "falpha": 0.0
    },
    "grassColor": {
      "value": -15987700,
      "falpha": 0.0
    },
    "foliageColor": {
      "value": -15987700,
      "falpha": 0.0
    },
    "waterColor": {
      "value": -15987700,
      "falpha": 0.0
    },
    "waterFogColor": {
      "value": -15987700,
      "falpha": 0.0
    },
    "treesPerChunk": 0,
    "grassPerChunk": 0,
    "seagrassPerChunk": 0,
    "flowersPerChunk": 0,
    "mushroomsPerChunk": 0,
    "bigMushroomsChunk": 0,
    "sandPathcesPerChunk": 0,
    "gravelPatchesPerChunk": 0,
    "reedsPerChunk": 0,
    "cactiPerChunk": 0,
    "rainingPossibility": 0.5,
    "temperature": 2.0,
    "baseHeight": 0.0,
    "heightVariation": 0.0,
    "spawnBiome": true,
    "biomeWeight": 64,
    "biomeType": "DESERT",
    "biomeCategory": "NONE",
    "parent": {
      "value": "No parent"
    },
    "spawnStronghold": false,
    "spawnMineshaft": false,
    "spawnPillagerOutpost": false,
    "villageType": "none",
    "spawnWoodlandMansion": false,
    "spawnJungleTemple": false,
    "spawnDesertPyramid": false,
    "spawnIgloo": false,
    "spawnOceanMonument": false,
    "spawnShipwreck": false,
    "oceanRuinType": "NONE",
    "biomeDictionaryTypes": [],
    "defaultFeatures": [],
    "spawnEntries": []
  }
}