{
  "_fv": 13,
  "_type": "dimension",
  "definition": {
    "portalFrame": {
      "value": ""
    },
    "portalParticles": {
      "value": "PORTAL"
    },
    "portalLuminance": 0.0,
    "portalSound": {
      "value": "block.portal.ambient"
    },
    "igniterName": "Farmingwood Portal Igniter",
    "igniterTab": {
      "value": "TOOLS"
    },
    "texture": "",
    "portalTexture": "",
    "enablePortal": false,
    "biomesInDimension": [
      {
        "value": "forest"
      },
      {
        "value": "bamboo_jungle_hills"
      },
      {
        "value": "snowy_tundra"
      },
      {
        "value": "forest_hills"
      },
      {
        "value": "jungle"
      },
      {
        "value": "birch_forest"
      }
    ],
    "worldGenType": "Normal world gen",
    "mainFillerBlock": {
      "value": "Blocks.LOG"
    },
    "fluidBlock": {
      "value": "Blocks.FLOWING_WATER"
    },
    "airColor": {
      "value": -4138753,
      "frgbvalue": [
        0.753,
        0.847,
        1.0
      ],
      "fvalue": [
        0.753,
        0.847,
        1.0
      ],
      "falpha": 1.0
    },
    "canRespawnHere": true,
    "hasFog": false,
    "hasWeather": true,
    "isDark": false,
    "doesWaterVaporize": false,
    "sleepResult": "DENY",
    "hasSkyLight": false,
    "imitateOverworldBehaviour": false,
    "onPlayerEntersDimension": {
      "name": "FarmingwoodPlayerEntersDimension"
    }
  }
}