{
  "_fv": 13,
  "_type": "recipe",
  "definition": {
    "recipeType": "Crafting",
    "xpReward": 0.0,
    "cookingTime": 200,
    "recipeRetstackSize": 1,
    "group": "",
    "recipeShapeless": true,
    "recipeSlots": [
      {
        "value": ""
      },
      {
        "value": "Blocks.STONE_SLAB"
      },
      {
        "value": ""
      },
      {
        "value": ""
      },
      {
        "value": "Blocks.GRASS"
      },
      {
        "value": ""
      },
      {
        "value": ""
      },
      {
        "value": ""
      },
      {
        "value": ""
      }
    ],
    "recipeReturnStack": {
      "value": "CUSTOM:Modernblock100"
    },
    "name": "modern_block_100_recipe",
    "namespace": "mod"
  }
}