{
  "_fv": 13,
  "_type": "recipe",
  "definition": {
    "recipeType": "Crafting",
    "xpReward": 0.0,
    "cookingTime": 200,
    "recipeRetstackSize": 1,
    "group": "",
    "recipeShapeless": false,
    "recipeSlots": [
      {
        "value": "Blocks.WEB"
      },
      {
        "value": "Items.GOLD_INGOT"
      },
      {
        "value": "Blocks.WEB"
      },
      {
        "value": "Items.GOLD_INGOT"
      },
      {
        "value": "Items.COMPASS"
      },
      {
        "value": "Items.GOLD_INGOT"
      },
      {
        "value": "Blocks.WEB"
      },
      {
        "value": "Items.GOLD_INGOT"
      },
      {
        "value": "Blocks.WEB"
      }
    ],
    "recipeReturnStack": {
      "value": "CUSTOM:Playerfrezer"
    },
    "name": "playerfreezerrecipe",
    "namespace": "mod"
  }
}